funnylog/__init__.py
funnylog/__version__.py
funnylog/conf.py
funnylog-2024.5.24.dist-info/METADATA
funnylog-2024.5.24.dist-info/WHEEL
funnylog-2024.5.24.dist-info/licenses/LICENSE
funnylog-2024.5.24.dist-info/licenses/NOTICE
funnylog-2024.5.24.dist-info/RECORD
