Metadata-Version: 2.1
Name: funnylog
Version: 2024.5.24
Summary: PaddleOCR-RPC
Project-URL: Source, https://github.com/linuxdeepin/funnylog
Project-URL: Documentation, https://linuxdeepin.github.io/funnylog
Author-email: mikigo <1964191531@qq.com>
License-File: LICENSE
License-File: NOTICE
Classifier: License :: OSI Approved :: Apache Software License
Classifier: Operating System :: OS Independent
Classifier: Programming Language :: Python :: 3
Requires-Python: >=3.6
Requires-Dist: allure-pytest
Provides-Extra: doc
Requires-Dist: mkdocs-material; extra == 'doc'
Provides-Extra: test
Requires-Dist: pytest; extra == 'test'
